QuDAP/StartGUI.py
QuDAP/__init__.py
QuDAP/initalization.py
QuDAP/requirements.txt
QuDAP/GUI/Dashboard/Dashboard.py
QuDAP/GUI/Dashboard/QLabel.qss
QuDAP/GUI/Dashboard/QLabel_1.qss
QuDAP/GUI/ETO/ETO.py
QuDAP/GUI/FMR/DataSorting.py
QuDAP/GUI/FMR/FMR.py
QuDAP/GUI/Icon/ASLR.svg
QuDAP/GUI/Icon/AdobeStock_549927879.ai
QuDAP/GUI/Icon/Dashboard.svg
QuDAP/GUI/Icon/Dashboard_Dark.svg
QuDAP/GUI/Icon/ETO.svg
QuDAP/GUI/Icon/ETO_Dark.svg
QuDAP/GUI/Icon/FMR.svg
QuDAP/GUI/Icon/FMR_Dark.svg
QuDAP/GUI/Icon/GPIB.svg
QuDAP/GUI/Icon/PPMS.svg
QuDAP/GUI/Icon/PPMS_Dark.svg
QuDAP/GUI/Icon/QEP.svg
QuDAP/GUI/Icon/SHG.svg
QuDAP/GUI/Icon/SHG_Dark.svg
QuDAP/GUI/Icon/TCPIP.svg
QuDAP/GUI/Icon/USB.svg
QuDAP/GUI/Icon/VSM.svg
QuDAP/GUI/Icon/VSM_Dark.svg
QuDAP/GUI/Icon/activity.svg
QuDAP/GUI/Icon/airplay.svg
QuDAP/GUI/Icon/alert-circle.svg
QuDAP/GUI/Icon/alert-octagon.svg
QuDAP/GUI/Icon/alert-triangle.svg
QuDAP/GUI/Icon/align-center.svg
QuDAP/GUI/Icon/align-justify.svg
QuDAP/GUI/Icon/align-left.svg
QuDAP/GUI/Icon/align-right.svg
QuDAP/GUI/Icon/anchor.svg
QuDAP/GUI/Icon/aperture.svg
QuDAP/GUI/Icon/archive.svg
QuDAP/GUI/Icon/arrow-down-circle.svg
QuDAP/GUI/Icon/arrow-down-left.svg
QuDAP/GUI/Icon/arrow-down-right.svg
QuDAP/GUI/Icon/arrow-down.svg
QuDAP/GUI/Icon/arrow-left-circle.svg
QuDAP/GUI/Icon/arrow-left.svg
QuDAP/GUI/Icon/arrow-right-circle.svg
QuDAP/GUI/Icon/arrow-right.svg
QuDAP/GUI/Icon/arrow-up-circle.svg
QuDAP/GUI/Icon/arrow-up-left.svg
QuDAP/GUI/Icon/arrow-up-right.svg
QuDAP/GUI/Icon/arrow-up.svg
QuDAP/GUI/Icon/at-sign.svg
QuDAP/GUI/Icon/award.svg
QuDAP/GUI/Icon/background.jpg
QuDAP/GUI/Icon/background2.jpg
QuDAP/GUI/Icon/bar-chart-2.svg
QuDAP/GUI/Icon/bar-chart.svg
QuDAP/GUI/Icon/battery-charging.svg
QuDAP/GUI/Icon/battery.svg
QuDAP/GUI/Icon/bell-off.svg
QuDAP/GUI/Icon/bell.svg
QuDAP/GUI/Icon/bluetooth.svg
QuDAP/GUI/Icon/bold.svg
QuDAP/GUI/Icon/book-open.svg
QuDAP/GUI/Icon/book.svg
QuDAP/GUI/Icon/bookmark.svg
QuDAP/GUI/Icon/box.svg
QuDAP/GUI/Icon/briefcase.svg
QuDAP/GUI/Icon/calendar.svg
qudap-0.0.5.dist-info/METADATA
qudap-0.0.5.dist-info/WHEEL
qudap-0.0.5.dist-info/licenses/LICENSE
qudap-0.0.5.dist-info/RECORD
