Metadata-Version: 2.3
Name: QuDAP
Version: 0.0.5
Summary: Quantum Materials Data Acquisition and Processing (QuDAP), a Python-based and open-source software package, is designed to control and automate material characterizations based on the Physical Property Measurement System (PPMS).
Project-URL: Homepage, https://github.com/CharlieGPA40/QuDAP
Project-URL: Issues, https://github.com/CharlieGPA40/QuDAP/issues
Author-email: Chunli Tang <chunli.tang@auburn.edu>
License-File: LICENSE
Classifier: License :: OSI Approved :: Apache Software License
Classifier: Operating System :: OS Independent
Classifier: Programming Language :: Python :: 3
Requires-Python: >=3.10
